codecriticAI/__init__.py
codecriticAI/main.py
codecriticAI/aireviewer/__init__.py
codecriticAI/aireviewer/reviewer.py
codecriticAI/gitops/__init__.py
codecriticAI/gitops/git_ops.py
codecriticAI/reportgenerator/__init__.py
codecriticAI/reportgenerator/html_generator.py
codecriticai-0.0.3.dist-info/licenses/LICENSE
codecriticai-0.0.3.dist-info/METADATA
codecriticai-0.0.3.dist-info/WHEEL
codecriticai-0.0.3.dist-info/entry_points.txt
codecriticai-0.0.3.dist-info/top_level.txt
codecriticai-0.0.3.dist-info/RECORD
