Metadata-Version: 2.4
Name: codecriticAI
Version: 0.0.3
Summary: An AI Code Review tool using OpenAI
Home-page: https://github.com/mihir20/codecriticAI
Author: Mihir Gandhi
Author-email: mihir20121997@gmail.com
Classifier: Programming Language :: Python :: 3
Classifier: License :: OSI Approved :: MIT License
Classifier: Operating System :: OS Independent
Requires-Python: >=3.10
License-File: LICENSE
Requires-Dist: markdown
Requires-Dist: openai
Dynamic: author
Dynamic: author-email
Dynamic: classifier
Dynamic: description
Dynamic: description-content-type
Dynamic: home-page
Dynamic: license-file
Dynamic: requires-dist
Dynamic: requires-python
Dynamic: summary
